Metadata-Version: 1.1
Name: osm2paths
Version: 0.0.3
Summary: An automatic generator of JSON vector road network graph car tracks from OSM
Home-page: https://github.com/MikeNezumi/osm2tracks
Author: MikeFreeman
Author-email: michaelsvoboda42@gmail.com
License: MIT
Keywords: json,traffic,simulation,data graphs,osm
Platform: UNKNOWN
Classifier: Development Status :: 3 - Alpha
Classifier: Intended Audience :: Developers
Classifier: Operating System :: OS Independent
Classifier: License :: OSI Approved :: MIT License
Classifier: Programming Language :: Python :: 3
